pytransform/__info__.py
pytransform/__init__.py
pytransform/pytransform.py
cpyberry_pytransform-2.0.0.dist-info/LICENSE
cpyberry_pytransform-2.0.0.dist-info/METADATA
cpyberry_pytransform-2.0.0.dist-info/NOTICE
cpyberry_pytransform-2.0.0.dist-info/WHEEL
cpyberry_pytransform-2.0.0.dist-info/top_level.txt
cpyberry_pytransform-2.0.0.dist-info/RECORD
